logbro-0.1.0.dist-info/licenses/LICENSE
logmachine/__init__.py
logmachine/core.py
logbro-0.1.0.dist-info/METADATA
logbro-0.1.0.dist-info/WHEEL
logbro-0.1.0.dist-info/top_level.txt
logbro-0.1.0.dist-info/RECORD
