Metadata-Version: 2.4
Name: logbro
Version: 0.1.0
Summary: Collaborative, beautiful logging system for distributed developers
Author-email: Mugabo Gusenga <mugabo@bufferpunk.com>
Project-URL: Homepage, https://github.com/Scion-Kin/logbro
Project-URL: Documentation, https://github.com/Scion-Kin/logbro#readme
Project-URL: Source, https://github.com/Scion-Kin/logbro
Project-URL: Tracker, https://github.com/Scion-Kin/logbro/issues
Keywords: logging,devtools,collaborative,open source,cli,json,ansi
Classifier: Programming Language :: Python :: 3
Classifier: License :: OSI Approved :: MIT License
Classifier: Operating System :: OS Independent
Requires-Python: >=3.7
License-File: LICENSE
Dynamic: license-file
